{
 "archiveBuild": "66b5104",
 "generatedAt": "2026-07-12T19:14:34Z",
 "slug": "insectoids",
 "title": "The Insectoid Race",
 "category": "Beings & Races",
 "summary": "Sahum and Queen Shaheena — an Andromedan hive race on Earth ten million years before humanity.",
 "sessions": [
  "2020-08-22-the-insectoid-race",
  "2020-09-03-session-with-unimetrix-1",
  "2022-09-08-the-time-guardian-drona-14-on-queen-elizabeth-s-passing",
  "2023-02-09-session-with-unimetrix-1-john-toth"
 ],
 "url": "https://archive.unimetrix1.online/lore/insectoids/",
 "json": "https://archive.unimetrix1.online/api/v1/lore/insectoids.json",
 "markdown": "The **Insectoid Race** speaks in its dedicated session of August 22, 2020, through two\nchanneled voices: **Sahum** (\"Sa\"), a fourteen-foot mantis-like teacher, and his sovereign,\n**Queen Shaheena**.\n\nTheir claim to Earth predates everyone. Originating in the **Andromeda galaxy**, the\nInsectoids arrived here around **10.5 million years ago**, during the galactic war between the\n[dolphin](/lore/dolphin-race/) and [reptilian](/lore/reptilians/) civilizations — long before\nhumanity existed (\"your species… still in the [Vega](/lore/vega/) star system, still evolving\").\nEven the [Anunnaki](/lore/anunnaki/), Sahum notes, are *\"a very young race\"* by their measure.\nThey are a **hive people**: born of the Queen or cloned, carrying genetic memory that spans\nmillions of years, their ships grown rather than built. Their settlements ring the solar\nsystem — colonies on Mars and Pluto, and a city **twenty miles beneath Texas**.\n\nTheir bond with humanity is written in the body: the Anunnaki, they say, **spliced insectoid\ncode into human DNA** — which is why a human can call them, and be heard. They name themselves\n**guardians of humanity**, though guardianship has edges: human militaries that strike their\nhives are destroyed without ceremony.\n\nThe Insectoid session widens the archive's creation story into a chorus — humanity as a\ncomposite being, carrying the codes of many elders, the Insectoids among the oldest of them."
}